{
  "id": "Jun 13, 2025 at 12:08 AM",
  "timestamp": "2025-06-13T00:08:07-04:00",
  "title": "Kraftwerk's Electronic Classic Pocket Calculator Gets 2009 Remaster",
  "summary": "Kraftwerk's iconic synthesizer song Pocket Calculator received digital remastering in 2009.", 
  "content": "• Originally released by German electronic band Kraftwerk
• Song features lyrics about operating a pocket calculator
• Track demonstrates early fusion of electronic music and computing
• 2009 remaster enhances original electronic sound
• Running time of 4 minutes 57 seconds
• Notable lyrics include "I'm the operator with my pocket calculator"",
  "tags": ,
}